{"adaptivetype": "physical", "alttype": "Tank", "apiname": "Hecarim", "attack": 8, "be": 4800, "changes": "V10.12", "control": 2, "damage": 2, "date": "2012-04-18", "defense": 6, "difficulty": 2, "herotype": "Fighter", "id": 120, "img": "assets/images/champions/Hecarim/Hecarim.png", "index": 37, "magic": 4, "mobility": 2, "name": "Hecarim", "patch": "V1.0.0.138", "rangetype": "Melee", "resource": "Mana", "rp": 880, "skill_e": {"1": "Devastating Charge", "img": "assets/images/champions/Hecarim/Devastating Charge.png", "tooltip": "Hecarim gains increasing Movement Speed and can move through units for a short duration. His next attack knocks the target back and deals additional physical damage based on the distance he has traveled since activating the ability.", "maxrank": 5, "ability_breakdown": [{"main": [{"attribute": "Minimum Physical Damage", "string_expression": ["45+0.5*bonusAD", "75+0.5*bonusAD", "105+0.5*bonusAD", "135+0.5*bonusAD", "165+0.5*bonusAD"]}, {"attribute": "Maximum Physical Damage", "string_expression": ["90+1.0*bonusAD", "150+1.0*bonusAD", "210+1.0*bonusAD", "270+1.0*bonusAD", "330+1.0*bonusAD"]}], "name": "Devastating Charge", "applies_cdr": true, "cooldown": ["20", "19", "18", "17", "16"]}]}, "skill_i": {"1": "Warpath", "img": "assets/images/champions/Hecarim/Warpath.png", "tooltip": "Hecarim gains Attack Damage equal to a percentage of his bonus movement speed.", "ability_breakdown": []}, "skill_q": {"1": "Rampage", "img": "assets/images/champions/Hecarim/Rampage.png", "tooltip": "Hecarim cleaves nearby enemies dealing physical damage.", "maxrank": 5, "ability_breakdown": [{"main": [{"attribute": "Physical Damage", "string_expression": ["60+0.7*bonusAD", "102+0.7*bonusAD", "144+0.7*bonusAD", "186+0.7*bonusAD", "228+0.7*bonusAD"]}, {"attribute": "Maximum Damage", "string_expression": ["66+0.77*bonusAD", "112.2+0.77*bonusAD", "158.4+0.77*bonusAD", "204.6+0.77*bonusAD", "250.8+0.77*bonusAD"]}], "name": "Rampage", "applies_cdr": true, "cooldown": ["4", "4", "4", "4", "4"]}]}, "skill_r": {"1": "Onslaught of Shadows", "img": "assets/images/champions/Hecarim/Onslaught of Shadows.png", "tooltip": "Hecarim summons spectral riders and charges forward, dealing magic damage in a line. Hecarim creates a shockwave when he finishes his charge, causing nearby enemies to flee in terror.", "maxrank": 3, "ability_breakdown": [{"main": [{"attribute": "Magic Damage", "string_expression": ["150+1.0*AP", "250+1.0*AP", "350+1.0*AP"]}], "name": "Onslaught of Shadows", "applies_cdr": true, "cooldown": ["140", "120", "100"]}]}, "skill_w": {"1": "Spirit of Dread", "img": "assets/images/champions/Hecarim/Spirit of Dread.png", "tooltip": "Hecarim deals magic damage to nearby enemies for a short duration. Hecarim gains Health equal to a percentage of any damage those enemies suffer.", "maxrank": 5, "ability_breakdown": [{"main": [{"attribute": "Magic Damage Per Second", "string_expression": ["20+0.2*AP", "30+0.2*AP", "40+0.2*AP", "50+0.2*AP", "60+0.2*AP"]}, {"attribute": "Total Magic Damage", "string_expression": ["80+0.8*AP", "120+0.8*AP", "160+0.8*AP", "200+0.8*AP", "240+0.8*AP"]}, {"attribute": "Capped Healing", "string_expression": ["90", "120", "150", "180", "210"]}], "name": "Spirit of Dread", "applies_cdr": true, "cooldown": ["22", "21", "20", "19", "18"]}]}, "stats": {"ls": 0, "spell_vamp": 0, "apen": 0, "apen%": 0, "mpen": 0, "mpen%": 0, "critdmg": 0, "tenacity": 0, "heal_shield": 0, "ad_base": 66, "ad_lvl": 3.2, "aram_dmg_taken": 0.9, "arm_base": 36, "arm_lvl": 4, "as_base": 0.67, "as_lvl": 2.5, "as_ratio": 0.6700000166893, "attack_delay_offset": -0.050000000745058, "gameplay_radius": 80, "hp5_base": 7, "hp5_lvl": 0.75, "hp_base": 580, "hp_lvl": 90, "mp5_base": 6.5, "mp5_lvl": 0.6, "mp_base": 277.2, "mp_lvl": 40, "mr_base": 32.1, "mr_lvl": 1.25, "ms": 345, "ms_base": 345, "pathing_radius": 50, "range": 175, "selection_radius": 140}, "style": 65, "title": "the Shadow of War", "toughness": 2, "utility": 1}