{"adaptivetype": "Physical", "alttype": "Fighter", "apiname": "Qiyana", "attack": 0, "be": 6300, "changes": "V10.13", "control": 2, "damage": 3, "date": "2019-06-28", "defense": 2, "difficulty": 2, "herotype": "Assassin", "id": 246, "img": "assets/images/champions/Qiyana/Qiyana.png", "index": 89, "magic": 4, "mobility": 2, "name": "Qiyana", "patch": "V9.13", "rangetype": "Melee", "resource": "Mana", "rp": 975, "skill_e": {"1": "Audacity", "img": "assets/images/champions/Qiyana/Audacity.png", "tooltip": "Qiyana dashes to an enemy and damaging them.", "maxrank": 5, "ability_breakdown": [{"main": [{"attribute": "Physical Damage", "string_expression": ["60 + 70% bonus AD", "95 + 70% bonus AD", "130 + 70% bonus AD", "165 + 70% bonus AD", "200 + 70% bonus AD"]}], "name": "Audacity"}]}, "skill_i": {"1": "Royal Privilege", "img": "assets/images/champions/Qiyana/Royal Privilege.png", "tooltip": "Qiyana's basic attacks and damaging abilities deal bonus physical damage.", "ability_breakdown": []}, "skill_q": {"1": "Edge of Ixtal", "2": "Elemental Wrath", "img": "assets/images/champions/Qiyana/Edge of Ixtal.png", "tooltip": "Qiyana swings her weapoon, dealing damage with a bonus effect based on the chosen element.", "maxrank": 5, "ability_breakdown": [{"main": [{"attribute": "Physical Damage", "string_expression": ["60 + 90% bonus AD", "85 + 90% bonus AD", "110 + 90% bonus AD", "135 + 90% bonus AD", "160 + 90% bonus AD"]}, {"attribute": "Reduced Damage", "string_expression": ["45 + 67.5% bonus AD", "63.75 + 67.5% bonus AD", "82.5 + 67.5% bonus AD", "101.25 + 67.5% bonus AD", "120 + 67.5% bonus AD"]}], "name": "Edge of Ixtal"}, {"form": [{"attribute": "Physical Damage", "string_expression": ["60 + 90% bonus AD", "85 + 90% bonus AD", "110 + 90% bonus AD", "135 + 90% bonus AD", "160 + 90% bonus AD"]}, {"attribute": "Reduced Damage", "string_expression": ["45 + 67.5% bonus AD", "63.75 + 67.5% bonus AD", "82.5 + 67.5% bonus AD", "101.25 + 67.5% bonus AD", "120 + 67.5% bonus AD"]}, {"attribute": "Bonus Damage", "string_expression": ["36 + 54% bonus AD", "51 + 54% bonus AD", "66 + 54% bonus AD", "81 + 54% bonus AD", "96 + 54% bonus AD"]}, {"attribute": "Total Damage", "string_expression": ["96 + 144% bonus AD", "136 + 144% bonus AD", "176 + 144% bonus AD", "216 + 144% bonus AD", "256 + 144% bonus AD"]}, {"attribute": "Total Damage to targets beyond the first", "string_expression": ["81 + 121.5% bonus AD", "114.75 + 121.5% bonus AD", "148.5 + 121.5% bonus AD", "182.25 + 121.5% bonus AD", "216 + 121.5% bonus AD"]}], "name": "Elemental Wrath"}]}, "skill_r": {"1": "Supreme Display of Talent", "img": "assets/images/champions/Qiyana/Supreme Display of Talent.png", "tooltip": "Qiyana sends a windblast in the target directions knocking back enemies and stopping upon hitting terrain. This sends a shockwave around the border of the terrain dealing damage and stunning any targets hit.", "maxrank": 3, "ability_breakdown": [{"main": [{"attribute": "Physical Damage", "string_expression": ["100 + 170% bonus AD + 10% of target's maximum health", "170 + 170% bonus AD + 10% of target's maximum health", "240 + 170% bonus AD + 10% of target's maximum health"]}, {"attribute": "Capped percentage damage", "string_expression": ["500", "750", "1000"]}], "name": "Supreme Display of Talent"}]}, "skill_w": {"1": "Terrashape", "img": "assets/images/champions/Qiyana/Terrashape.png", "tooltip": "Qiyana dashes to a target location and enchants her weapon with an element. Her attacks and abilities deal bonus damage while her weapon is enchanted.", "maxrank": 5, "ability_breakdown": [{"main": [{"attribute": "Bonus Attack Speed", "string_expression": ["5%", "10%", "15%", "20%", "25%"]}, {"attribute": "Bonus Magic Damage", "string_expression": ["8 + 20% bonus AD + 30% AP", "16 + 20% bonus AD + 30% AP", "24 + 20% bonus AD + 30% AP", "32 + 20% bonus AD + 30% AP", "40 + 20% bonus AD + 30% AP"]}, {"attribute": "Bonus Movement Speed", "string_expression": ["5%", "6.25%", "7.5%", "8.75%", "10%"]}], "name": "Terrashape"}]}, "stats": {"ls": 0, "spell_vamp": 0, "apen": 0, "apen%": 0, "mpen": 0, "mpen%": 0, "critdmg": 0, "tenacity": 0, "heal_shield": 0, "ad_base": 64, "ad_lvl": 3.1, "aram_dmg_dealt": 1.1, "aram_dmg_taken": 0.9, "arm_base": 28, "arm_lvl": 3.5, "as_base": 0.625, "as_lvl": 2.1, "as_ratio": 0.625, "attack_cast_time": 0.230000004172325, "attack_total_time": 1.5, "hp5_base": 8.5, "hp5_lvl": 0.65, "hp_base": 590, "hp_lvl": 90, "mp5_base": 8, "mp5_lvl": 0.7, "mp_base": 320, "mp_lvl": 50, "mr_base": 32.1, "mr_lvl": 1.25, "ms": 335, "ms_base": 335, "nb_dmg_taken": 0.95, "ofa_dmg_taken": 0.95, "pathing_radius": 35, "range": 150, "selection_radius": 120, "urf_dmg_dealt": 1.05, "urf_dmg_taken": 0.95}, "style": 70, "title": "Empress of the Elements", "toughness": 1, "utility": 1}