{"allowed_to": {"melee": true, "ranged": true}, "apiname": "liandrysanguish", "gold": 3400, "id": "6653", "img": "http://ddragon.leagueoflegends.com/cdn/10.24.1/img/item/6653.png", "index": 85, "item_group": "mythic", "name": "Liandry's Anguish", "passives": [{"mythic": false, "name": "torment", "stats": {}, "unique": true}, {"mythic": true, "name": "passive", "stats": {"ability_haste": 5}, "unique": true}], "rank": "mythic", "search_types": "ability power,ability haste,mana", "stackable": false, "stacked": false, "stats": {"ap": 80, "mp": 600, "ability_haste": 20}, "tags": "", "tooltip": "Liandry's Anguish<br><br>Cost: 3400<br>+20 Ability Haste<br>+80 Ability Power<br>+600 Mana<br><br>UNIQUE Passive - Torment: Dealing ability damage burns enemies, causing them to take[ 60 (+ 6% AP) (+ 4% target's maximum health) magic damage over 4 seconds ][ 7.5 (+ 0.75% AP) (+ 0.5% target's maximum health) magic damage every 0.5 seconds for 4 seconds ]and the user to ignore 5% of their magic resistance, increasing by 5% per second over 4 seconds, up to 15%.<br><br>UNIQUE Passive: Empowers your other Legendary items with 5 ability haste.", "visible": true}